cnn_archs/__init__.py
cnn_archs/baseline.py
cnn_archs/baseline_v.py
cnn_archs/baseline_v2.py
cnn_archs/baseline_v3.py
cnn_archs/baseline_v4.py
cnn_archs/basic.py
cnn_archs/hourglass_wores.py
cnn_archs/hourglass_wores_synth.py
cnn_archs/hourglass_wores_v2.py
cnn_archs/hourglass_wores_v3.py
cnn_archs/hourglass_wres.py
cnn_archs/hourglass_wres_k5.py
cnn_archs/hourglass_wres_patch.py
cnn_archs/hourglass_wres_synth.py
cnn_archs/hourglass_wres_tr.py
cnn_archs/hourglass_wres_v2.py
cnn_archs/hourglass_wres_v3.py
cnn_archs/leap.py
cnn_archs/unet_v.py
cnn_archs/unet_v2.py
cnn_archs/unet_v2_synth.py
cnn_archs/unet_v3.py
cnn_archs/unet_v4.py
cnn_archs/unet_v4_int_sup.py
cnn_archs/unet_v5_int_sup.py
cnn_archs/unet_v_k5.py
cnn_archs/unet_v_patch.py
cnn_archs/unet_v_synth.py
cnn_archs/unet_v_tr.py
cnn_archs/unet_v_tr_v2.py
niddl/__init__.py
niddl/inference.py
niddl/train.py
niddl/utils.py
niddl/utils_inference.py
NIDDL-0.1.8.dist-info/LICENSE
NIDDL-0.1.8.dist-info/METADATA
NIDDL-0.1.8.dist-info/WHEEL
NIDDL-0.1.8.dist-info/top_level.txt
NIDDL-0.1.8.dist-info/RECORD
