Metadata-Version: 2.1
Name: NIDDL
Version: 0.1.8
Summary: Neuro Imaging Denoising via Deep Learning (NIDDL)
Home-page: https://github.com/shiveshc/whole-brain_DeepDenoising
Author: Shivesh Chaudhary
Author-email: shiveshc@gmail.com
License: MIT
Keywords: denoising,whole-brain imaging,calcium imaging,celegans,deep learning,volumetric imaging,microscopy
Classifier: Development Status :: 3 - Alpha
Classifier: Intended Audience :: Developers
Classifier: License :: OSI Approved :: MIT License
Classifier: Programming Language :: Python :: 3
License-File: LICENSE
